sphinxcontrib/autodoc_inherit_overload.py
sphinxcontrib_autodoc_inherit_overload-2023.4.dist-info/LICENSE.txt
sphinxcontrib_autodoc_inherit_overload-2023.4.dist-info/WHEEL
sphinxcontrib_autodoc_inherit_overload-2023.4.dist-info/METADATA
sphinxcontrib_autodoc_inherit_overload-2023.4.dist-info/RECORD
