Metadata-Version: 2.1
Name: sphinxcontrib.autodoc_inherit_overload
Version: 2023.4
Summary: Sphinx extension to render inherited overloads with autodoc.
Keywords: sphinx,sphinxcontrib,autodoc,typing,overload
Author-email: Nicolas Tessore <n.tessore@ucl.ac.uk>
Requires-Python: >=3.11
Classifier: License :: OSI Approved :: MIT License
Project-URL: Homepage, https://github.com/ntessore/autodoc_inherit_overload
Project-URL: Issues, https://github.com/ntessore/autodoc_inherit_overload/issues
